dmt/__init__.py
dmt/attribute.py
dmt/blueprint.py
dmt/blueprint_attribute.py
dmt/copier.py
dmt/dimension.py
dmt/dmt_reader.py
dmt/dmt_writer.py
dmt/entity.py
dmt/enum_attribute.py
dmt/namedentity.py
dmt/blueprints/__init__.py
dmt/blueprints/entity.py
dmt/blueprints/namedentity.py
dmt/h5/__init__.py
dmt/h5/h5_reader.py
dmt/h5/h5_writer.py
dmtpy-0.3.5.dist-info/METADATA
dmtpy-0.3.5.dist-info/WHEEL
dmtpy-0.3.5.dist-info/licenses/LICENSE
dmtpy-0.3.5.dist-info/RECORD
