Metadata-Version: 2.4
Name: dmtpy
Version: 0.3.5
Summary: Python runtime library for SIMOS based DMT models
Project-URL: Homepage, https://github.com/SINTEF/dmtpy
Project-URL: Repository, https://github.com/SINTEF/dmtpy
Author: SINTEF Ocean
License: MIT
License-File: LICENSE
Classifier: License :: OSI Approved :: MIT License
Classifier: Operating System :: OS Independent
Classifier: Programming Language :: Python :: 3
Requires-Python: >=3.8
Requires-Dist: h5py>=3.7.0
Requires-Dist: numpy<1.25.0,>=1.21.0; python_version < '3.9'
Requires-Dist: numpy>=1.25.0; python_version >= '3.9'
